LICENSE
NOTICE
README.md
pyproject.toml
setup.py
/data/groundingdino-cu128/groundingdino/models/GroundingDINO/csrc/cuda_version.cu
/data/groundingdino-cu128/groundingdino/models/GroundingDINO/csrc/vision.cpp
/data/groundingdino-cu128/groundingdino/models/GroundingDINO/csrc/MsDeformAttn/ms_deform_attn_cpu.cpp
/data/groundingdino-cu128/groundingdino/models/GroundingDINO/csrc/MsDeformAttn/ms_deform_attn_cuda.cu
groundingdino/__init__.py
groundingdino/version.py
groundingdino/config/GroundingDINO_SwinT_OGC.py
groundingdino/datasets/transforms.py
groundingdino/models/__init__.py
groundingdino/models/registry.py
groundingdino/models/GroundingDINO/__init__.py
groundingdino/models/GroundingDINO/bertwarper.py
groundingdino/models/GroundingDINO/fuse_modules.py
groundingdino/models/GroundingDINO/groundingdino.py
groundingdino/models/GroundingDINO/ms_deform_attn.py
groundingdino/models/GroundingDINO/transformer.py
groundingdino/models/GroundingDINO/transformer_vanilla.py
groundingdino/models/GroundingDINO/utils.py
groundingdino/models/GroundingDINO/backbone/__init__.py
groundingdino/models/GroundingDINO/backbone/backbone.py
groundingdino/models/GroundingDINO/backbone/position_encoding.py
groundingdino/models/GroundingDINO/backbone/swin_transformer.py
groundingdino/models/GroundingDINO/csrc/cuda_version.cu
groundingdino/models/GroundingDINO/csrc/vision.cpp
groundingdino/models/GroundingDINO/csrc/MsDeformAttn/ms_deform_attn.h
groundingdino/models/GroundingDINO/csrc/MsDeformAttn/ms_deform_attn_cpu.cpp
groundingdino/models/GroundingDINO/csrc/MsDeformAttn/ms_deform_attn_cpu.h
groundingdino/models/GroundingDINO/csrc/MsDeformAttn/ms_deform_attn_cuda.cu
groundingdino/models/GroundingDINO/csrc/MsDeformAttn/ms_deform_attn_cuda.h
groundingdino/util/__init__.py
groundingdino/util/box_ops.py
groundingdino/util/get_tokenlizer.py
groundingdino/util/inference.py
groundingdino/util/logger.py
groundingdino/util/misc.py
groundingdino/util/slconfig.py
groundingdino/util/slio.py
groundingdino_cu128.egg-info/PKG-INFO
groundingdino_cu128.egg-info/SOURCES.txt
groundingdino_cu128.egg-info/dependency_links.txt
groundingdino_cu128.egg-info/not-zip-safe
groundingdino_cu128.egg-info/requires.txt
groundingdino_cu128.egg-info/top_level.txt
