Metadata-Version: 2.4
Name: groundingdino-cu128
Version: 0.2.0
Summary: Upgraded GroundingDINO for PyTorch 2.7 + CUDA 12.8 (maintained fork)
Author-email: ghostcipher1 <ghostcipher1@users.noreply.github.com>
Maintainer-email: ghostcipher1 <ghostcipher1@users.noreply.github.com>
License:                                  Apache License
Project-URL: Homepage, https://github.com/ghostcipher1/groundingdino-cu128
Project-URL: Repository, https://github.com/ghostcipher1/groundingdino-cu128
Project-URL: Issue Tracker, https://github.com/ghostcipher1/groundingdino-cu128/issues
Project-URL: Documentation, https://github.com/ghostcipher1/groundingdino-cu128#readme
Project-URL: Original Source, https://github.com/IDEA-Research/GroundingDINO
Keywords: computer-vision,object-detection,grounding,dino,transformer,pytorch,cuda
Classifier: Development Status :: 4 - Beta
Classifier: Intended Audience :: Developers
Classifier: Intended Audience :: Science/Research
Classifier: License :: OSI Approved :: Apache Software License
Classifier: Operating System :: POSIX :: Linux
Classifier: Programming Language :: Python :: 3
Classifier: Programming Language :: Python :: 3.9
Classifier: Programming Language :: Python :: 3.10
Classifier: Programming Language :: Python :: 3.11
Classifier: Programming Language :: Python :: 3.12
Classifier: Topic :: Scientific/Engineering :: Artificial Intelligence
Classifier: Topic :: Scientific/Engineering :: Image Recognition
Requires-Python: >=3.9
License-File: LICENSE
License-File: NOTICE
Requires-Dist: torch<2.8,>=2.7.0
Requires-Dist: torchvision>=0.18.0
Requires-Dist: transformers
Requires-Dist: addict
Requires-Dist: yapf
Requires-Dist: timm
Requires-Dist: numpy
Requires-Dist: opencv-python
Requires-Dist: supervision==0.4.0
Requires-Dist: pycocotools
Dynamic: license-file
